pdsniff/README.MD
pdsniff/__init__.py
pdsniff/requirements.txt
pdsniff/thirdparty.json
pdsniff-0.10.dist-info/LICENSE.rst
pdsniff-0.10.dist-info/METADATA
pdsniff-0.10.dist-info/WHEEL
pdsniff-0.10.dist-info/top_level.txt
pdsniff-0.10.dist-info/RECORD
