Metadata-Version: 2.1
Name: pdsniff
Version: 0.10
Summary: captures and processes network packets asynchronously using the Scapy library, and converts the results to a pandas DataFrame
Home-page: https://github.com/hansalemaos/pdsniff
Author: Johannes Fischer
Author-email: aulasparticularesdealemaosp@gmail.com
License: MIT
Keywords: network,sniffing
Classifier: Development Status :: 4 - Beta
Classifier: Programming Language :: Python :: 3 :: Only
Classifier: Programming Language :: Python :: 3.10
Classifier: Topic :: Software Development :: Libraries :: Python Modules
Classifier: Topic :: Utilities
License-File: LICENSE.rst
Requires-Dist: get-consecutive-filename
Requires-Dist: keyboard
Requires-Dist: kthread
Requires-Dist: kthread-sleep
Requires-Dist: pandas
Requires-Dist: scapy
Requires-Dist: tolerant-isinstance
